sheetsDB/__init__.py
sheetsDB/db.py
sheetsDB/synced.py
sheetsDB-0.1.1.dist-info/LICENSE
sheetsDB-0.1.1.dist-info/METADATA
sheetsDB-0.1.1.dist-info/WHEEL
sheetsDB-0.1.1.dist-info/top_level.txt
sheetsDB-0.1.1.dist-info/RECORD
