Metadata-Version: 2.1
Name: sheetsDB
Version: 0.1.1
Summary: UNKNOWN
Home-page: UNKNOWN
Author: UNKNOWN
Author-email: fedor.tryfanau@gmail.com
License: UNKNOWN
Platform: UNKNOWN
Requires-Dist: gspread
Requires-Dist: oauth2client
